biosteam/__init__.py
biosteam/_facility.py
biosteam/_flowsheet.py
biosteam/_graphics.py
biosteam/_heat_utility.py
biosteam/_network.py
biosteam/_power_utility.py
biosteam/_preferences.py
biosteam/_settings.py
biosteam/_system.py
biosteam/_tea.py
biosteam/_temporary_connection.py
biosteam/_unit.py
biosteam/exceptions.py
biosteam/digraph/__init__.py
biosteam/digraph/digraph.css
biosteam/digraph/digraph.js
biosteam/digraph/digraph.py
biosteam/evaluation/__init__.py
biosteam/evaluation/_feature.py
biosteam/evaluation/_metric.py
biosteam/evaluation/_model.py
biosteam/evaluation/_name.py
biosteam/evaluation/_parameter.py
biosteam/evaluation/_state.py
biosteam/evaluation/_utils.py
biosteam/evaluation/evaluation_tools/__init__.py
biosteam/evaluation/evaluation_tools/in_parallel.py
biosteam/evaluation/evaluation_tools/parameter.py
biosteam/facilities/__init__.py
biosteam/facilities/_air_distribution_package.py
biosteam/facilities/_blowdown_mixer.py
biosteam/facilities/_boiler_turbogenerator.py
biosteam/facilities/_chemical_capital_investment.py
biosteam/facilities/_chilled_water_package.py
biosteam/facilities/_cleaning_in_place.py
biosteam/facilities/_cooling_tower.py
biosteam/facilities/_fire_water_tank.py
biosteam/facilities/_process_water_center.py
biosteam/facilities/_refrigeration_package.py
biosteam/facilities/systems.py
biosteam/facilities/hxn/__init__.py
biosteam/facilities/hxn/_heat_exchanger_network.py
biosteam/facilities/hxn/hxn_synthesis.py
biosteam/plots/__init__.py
biosteam/plots/ipython.html
biosteam/plots/plots.py
biosteam/plots/sankey.py
biosteam/plots/utils.py
biosteam/process_tools/__init__.py
biosteam/process_tools/bounded_numerical_specification.py
biosteam/process_tools/reactor_specification.py
biosteam/process_tools/segment.py
biosteam/process_tools/system_factory.py
biosteam/process_tools/system_mesh.py
biosteam/process_tools/unit_group.py
biosteam/process_tools/utils.py
biosteam/report/__init__.py
biosteam/report/plot.py
biosteam/report/table.py
biosteam-2.37.6.dist-info/LICENSE.txt
biosteam-2.37.6.dist-info/METADATA
biosteam-2.37.6.dist-info/WHEEL
biosteam-2.37.6.dist-info/top_level.txt
biosteam-2.37.6.dist-info/RECORD
