Metadata-Version: 2.1
Name: biosteam
Version: 2.37.6
Summary: The Biorefinery Simulation and Techno-Economic Analysis Modules
Home-page: https://github.com/BioSTEAMDevelopmentGroup/biosteam
Download-URL: https://github.com/BioSTEAMDevelopmentGroup/biosteam.git
Author: Yoel Cortes-Pena
Author-email: yoelcortes@gmail.com
License: MIT
Keywords: chemical process simulation,bioprocess engineering,mass and energy balance,material properties,phase equilibrium,CABBI,biorefinery,biofuel,bioproducts
Platform: Windows
Platform: Mac
Platform: Linux
Classifier: License :: OSI Approved :: University of Illinois/NCSA Open Source License
Classifier: Development Status :: 3 - Alpha
Classifier: Environment :: Console
Classifier: Topic :: Scientific/Engineering
Classifier: Topic :: Scientific/Engineering :: Chemistry
Classifier: Topic :: Scientific/Engineering :: Mathematics
Classifier: Intended Audience :: Developers
Classifier: Intended Audience :: Education
Classifier: Intended Audience :: Manufacturing
Classifier: Intended Audience :: Science/Research
Classifier: Natural Language :: English
Classifier: Operating System :: MacOS
Classifier: Operating System :: Microsoft :: Windows
Classifier: Operating System :: POSIX
Classifier: Operating System :: POSIX :: BSD
Classifier: Operating System :: POSIX :: Linux
Classifier: Operating System :: Unix
Classifier: Programming Language :: Python :: 3.9
Classifier: Programming Language :: Python :: 3.10
Classifier: Programming Language :: Python :: Implementation :: CPython
Classifier: Topic :: Education
Requires-Python: >=3.9
License-File: LICENSE.txt
Requires-Dist: IPython >=7.9.0
Requires-Dist: thermosteam <0.36.0,>=0.35.0
Requires-Dist: graphviz >=0.17
Requires-Dist: chaospy >=3.3.9
Requires-Dist: pyyaml
Provides-Extra: dev
Requires-Dist: biorefineries >=2.26.0 ; extra == 'dev'
Requires-Dist: sympy ; extra == 'dev'
Requires-Dist: sphinx ; extra == 'dev'
Requires-Dist: sphinx-multitoc-numbering ; extra == 'dev'
Requires-Dist: pydata-sphinx-theme ; extra == 'dev'
Requires-Dist: sphinx-design ; extra == 'dev'
Requires-Dist: pyyaml ; extra == 'dev'
Requires-Dist: pytest-cov ; extra == 'dev'
Requires-Dist: coveralls ; extra == 'dev'
Requires-Dist: SALib ; extra == 'dev'
